ttmtdb/__init__.py
ttmtdb/cnumba.py
ttmtdb/ttmtdb.py
ttmtdb/ttmtdbdata.py
ttmtdb-0.0.1.dist-info/METADATA
ttmtdb-0.0.1.dist-info/WHEEL
ttmtdb-0.0.1.dist-info/licenses/LICENSE
ttmtdb-0.0.1.dist-info/RECORD
