Metadata-Version: 2.4
Name: TTmTDB
Version: 0.0.1
Summary: Time difference between the TT and TDB time scales with a precision better han 200ns over 2 centuries.
Project-URL: Homepage, https://github.com/hesselberth/Inpop
Project-URL: Issues, https://github.com/hesselberth/Inpop/issues
Author-email: Marcel Hesselberth <hessel@physics.leidenuniv.nl>
License-File: LICENSE
Keywords: astrometry,astronomy,celestial navigation,mathematics,physics
Classifier: License :: OSI Approved :: GNU General Public License v3 or later (GPLv3+)
Classifier: Operating System :: OS Independent
Classifier: Programming Language :: Python :: 3
Classifier: Topic :: Scientific/Engineering :: Astronomy
Classifier: Topic :: Scientific/Engineering :: Mathematics
Classifier: Topic :: Scientific/Engineering :: Physics
Requires-Python: >=3.8
Requires-Dist: numba>0.56
Requires-Dist: numpy>1.21
